{"frames": [

{
	"filename": "bang.png",
	"frame": {"x":0,"y":0,"w":120,"h":89},
	"rotated": false,
	"trimmed": false,
	"spriteSourceSize": {"x":0,"y":0,"w":120,"h":89},
	"sourceSize": {"w":120,"h":89},
	"pivot": {"x":0.5,"y":0.5}
},
{
	"filename": "laserBlue04.png",
	"frame": {"x":0,"y":89,"w":13,"h":37},
	"rotated": false,
	"trimmed": false,
	"spriteSourceSize": {"x":0,"y":0,"w":13,"h":37},
	"sourceSize": {"w":13,"h":37},
	"pivot": {"x":0.5,"y":0.5}
},
{
	"filename": "meteorBrown_big1.png",
	"frame": {"x":13,"y":89,"w":101,"h":84},
	"rotated": false,
	"trimmed": false,
	"spriteSourceSize": {"x":0,"y":0,"w":101,"h":84},
	"sourceSize": {"w":101,"h":84},
	"pivot": {"x":0.5,"y":0.5}
},
{
	"filename": "meteorBrown_big3.png",
	"frame": {"x":0,"y":173,"w":89,"h":82},
	"rotated": false,
	"trimmed": false,
	"spriteSourceSize": {"x":0,"y":0,"w":89,"h":82},
	"sourceSize": {"w":89,"h":82},
	"pivot": {"x":0.5,"y":0.5}
},
{
	"filename": "meteorBrown_big4.png",
	"frame": {"x":0,"y":255,"w":98,"h":96},
	"rotated": false,
	"trimmed": false,
	"spriteSourceSize": {"x":0,"y":0,"w":98,"h":96},
	"sourceSize": {"w":98,"h":96},
	"pivot": {"x":0.5,"y":0.5}
},
{
	"filename": "meteorBrown_med1.png",
	"frame": {"x":0,"y":351,"w":43,"h":43},
	"rotated": false,
	"trimmed": false,
	"spriteSourceSize": {"x":0,"y":0,"w":43,"h":43},
	"sourceSize": {"w":43,"h":43},
	"pivot": {"x":0.5,"y":0.5}
},
{
	"filename": "meteorBrown_med3.png",
	"frame": {"x":43,"y":351,"w":45,"h":40},
	"rotated": false,
	"trimmed": false,
	"spriteSourceSize": {"x":0,"y":0,"w":45,"h":40},
	"sourceSize": {"w":45,"h":40},
	"pivot": {"x":0.5,"y":0.5}
},
{
	"filename": "meteorBrown_small1.png",
	"frame": {"x":88,"y":351,"w":28,"h":28},
	"rotated": false,
	"trimmed": false,
	"spriteSourceSize": {"x":0,"y":0,"w":28,"h":28},
	"sourceSize": {"w":28,"h":28},
	"pivot": {"x":0.5,"y":0.5}
},
{
	"filename": "meteorBrown_small2.png",
	"frame": {"x":0,"y":394,"w":29,"h":26},
	"rotated": false,
	"trimmed": false,
	"spriteSourceSize": {"x":0,"y":0,"w":29,"h":26},
	"sourceSize": {"w":29,"h":26},
	"pivot": {"x":0.5,"y":0.5}
},
{
	"filename": "meteorBrown_tiny1.png",
	"frame": {"x":29,"y":394,"w":18,"h":18},
	"rotated": false,
	"trimmed": false,
	"spriteSourceSize": {"x":0,"y":0,"w":18,"h":18},
	"sourceSize": {"w":18,"h":18},
	"pivot": {"x":0.5,"y":0.5}
},
{
	"filename": "meteorBrown_tiny2.png",
	"frame": {"x":47,"y":394,"w":16,"h":15},
	"rotated": false,
	"trimmed": false,
	"spriteSourceSize": {"x":0,"y":0,"w":16,"h":15},
	"sourceSize": {"w":16,"h":15},
	"pivot": {"x":0.5,"y":0.5}
},
{
	"filename": "playerShip2_orange.png",
	"frame": {"x":0,"y":420,"w":112,"h":75},
	"rotated": false,
	"trimmed": false,
	"spriteSourceSize": {"x":0,"y":0,"w":112,"h":75},
	"sourceSize": {"w":112,"h":75},
	"pivot": {"x":0.5,"y":0.5}
}],
"meta": {
	"app": "http://www.codeandweb.com/texturepacker",
	"version": "1.0",
	"image": "asteroids.png",
	"format": "RGBA8888",
	"size": {"w":128,"h":512},
	"scale": "1",
	"smartupdate": "$TexturePacker:SmartUpdate:23d22d95c6cb0801a5cd1be87ca21d41:5de8d64ea05054323df2174ccc94deee:3cb2167982f406a3d6627570b02f9be7$"
}
}
